{
  "project_info": {
    "project_number": "575147882005",
    "project_id": "praxis-donation-backend",
    "storage_bucket": "praxis-donation-backend.appspot.com"
  },
  "client": [
    {
      "client_info": {
        "mobilesdk_app_id": "1:575147882005:android:8489900cf6862bc890c01c",
        "android_client_info": {
          "package_name": "com.example.dashboardui"
        }
      },
      "oauth_client": [
        {
          "client_id": "575147882005-7lrpomuu4r65l7k8uivn0u183hdhg8ff.apps.googleusercontent.com",
          "client_type": 3
        }
      ],
      "api_key": [
        {
          "current_key": "AIzaSyCCuftl8mwI2qO2DX1f29NoPshnW1aMM74"
        }
      ],
      "services": {
        "appinvite_service": {
          "other_platform_oauth_client": [
            {
              "client_id": "575147882005-7lrpomuu4r65l7k8uivn0u183hdhg8ff.apps.googleusercontent.com",
              "client_type": 3
            },
            {
              "client_id": "575147882005-kug2dq0gtb6sarfjfvebub5r09772d1m.apps.googleusercontent.com",
              "client_type": 2,
              "ios_info": {
                "bundle_id": "com.example.dashboardui"
              }
            }
          ]
        }
      }
    }
  ],
  "configuration_version": "1"
}